<?xml version="1.0" encoding="UTF-8" standalone="no"?>
<!DOCTYPE TWaD_campaign_group_member_criteria_player_game_difficulty_types>
<root>
<edit_uuid>705cab57-6b0a-446b-a610-7b091eeae3a2</edit_uuid>
<agf_special_dependencies></agf_special_dependencies>
<field>
<field_uuid>{c7874344-8deb-4bc3-9cde-8b07dfe06ff0}</field_uuid>
<primary_key>1</primary_key>
<name>member</name>
<field_type>text</field_type>
<required>1</required>
<max_length>255</max_length>
<column_source_column>id</column_source_column>
<column_source_table>campaign_group_members</column_source_table>
<agf_link_to_dependency>0</agf_link_to_dependency>
<agf_link_to_dependents>0</agf_link_to_dependents>
<agf_done>1</agf_done>
<requires_startpos_reprocess>0</requires_startpos_reprocess>
<requires_campaign_map_reprocess>0</requires_campaign_map_reprocess>
</field>
<field>
<field_uuid>{b18bda58-265e-4838-af08-548d84a907a6}</field_uuid>
<primary_key>0</primary_key>
<name>player_game_difficulty_type</name>
<field_type>text</field_type>
<required>1</required>
<max_length>255</max_length>
<column_source_column>difficulty_type</column_source_column>
<column_source_table>player_game_difficulty_types</column_source_table>
<agf_link_to_dependency>0</agf_link_to_dependency>
<agf_link_to_dependents>1</agf_link_to_dependents>
<agf_done>1</agf_done>
<requires_startpos_reprocess>0</requires_startpos_reprocess>
<requires_campaign_map_reprocess>0</requires_campaign_map_reprocess>
</field>
</root>
