<?xml version="1.0" encoding="UTF-8" standalone="no"?>
<!DOCTYPE TWaD_dilemmas>
<root>
<edit_uuid>94bf307f-a0ec-4440-88a9-e369a1989c00</edit_uuid>
<include_all_records_in_retail>1</include_all_records_in_retail>
<field>
<field_uuid>{8461ad81-8dac-4aa7-81f3-9888488321a9}</field_uuid>
<primary_key>1</primary_key>
<name>key</name>
<field_type>text</field_type>
<required>1</required>
<max_length>255</max_length>
<requires_startpos_reprocess>0</requires_startpos_reprocess>
<requires_campaign_map_reprocess>0</requires_campaign_map_reprocess>
</field>
<field>
<field_uuid>{f65704eb-9958-422c-bea9-27f4681bd1f8}</field_uuid>
<primary_key>0</primary_key>
<name>localised_title</name>
<field_type>text</field_type>
<required>1</required>
<max_length>255</max_length>
<requires_startpos_reprocess>0</requires_startpos_reprocess>
<requires_campaign_map_reprocess>0</requires_campaign_map_reprocess>
</field>
<field>
<field_uuid>{fef28bc5-b819-48e8-889a-fc3a3c57b789}</field_uuid>
<primary_key>0</primary_key>
<name>localised_description</name>
<field_type>text</field_type>
<required>1</required>
<max_length>900000</max_length>
<requires_startpos_reprocess>0</requires_startpos_reprocess>
<requires_campaign_map_reprocess>0</requires_campaign_map_reprocess>
</field>
<field>
<field_uuid>{26e7ef3a-9632-420f-b124-ee1750e83695}</field_uuid>
<primary_key>0</primary_key>
<name>ui_image</name>
<field_type>text</field_type>
<required>1</required>
<max_length>255</max_length>
<requires_startpos_reprocess>0</requires_startpos_reprocess>
<requires_campaign_map_reprocess>0</requires_campaign_map_reprocess>
</field>
<field>
<field_uuid>{8374748f-3880-44bf-9bdb-91090f4de7a7}</field_uuid>
<primary_key>0</primary_key>
<name>generate</name>
<field_type>yesno</field_type>
<required>1</required>
<requires_startpos_reprocess>0</requires_startpos_reprocess>
<requires_campaign_map_reprocess>0</requires_campaign_map_reprocess>
</field>
<field>
<field_uuid>{b58cc1d6-2337-4c01-97fc-2d9f9e1e1fa6}</field_uuid>
<primary_key>0</primary_key>
<name>prioritized</name>
<field_type>yesno</field_type>
<required>1</required>
<default_value>false</default_value>
<requires_startpos_reprocess>0</requires_startpos_reprocess>
<requires_campaign_map_reprocess>0</requires_campaign_map_reprocess>
</field>
<field>
<field_uuid>{d945fca1-b84b-4a01-b495-7c11e38539dd}</field_uuid>
<primary_key>0</primary_key>
<name>event_category</name>
<field_type>text</field_type>
<required>0</required>
<max_length>255</max_length>
<column_source_column>category_key</column_source_column>
<column_source_table>cdir_events_categories</column_source_table>
<requires_startpos_reprocess>0</requires_startpos_reprocess>
<requires_campaign_map_reprocess>0</requires_campaign_map_reprocess>
</field>
<field>
<field_uuid>{0e8e91e0-63a1-4361-858f-13161539e0c7}</field_uuid>
<primary_key>0</primary_key>
<name>sound_popup_override</name>
<field_type>text</field_type>
<fragment_path>sound/events</fragment_path>
<required>0</required>
<max_length>255</max_length>
<requires_startpos_reprocess>0</requires_startpos_reprocess>
<requires_campaign_map_reprocess>0</requires_campaign_map_reprocess>
</field>
<field>
<field_uuid>{d676f1ca-bb4b-4dac-9601-6bd995b89bd1}</field_uuid>
<primary_key>0</primary_key>
<name>sound_click_override</name>
<field_type>text</field_type>
<fragment_path>sound/events</fragment_path>
<required>0</required>
<max_length>255</max_length>
<requires_startpos_reprocess>0</requires_startpos_reprocess>
<requires_campaign_map_reprocess>0</requires_campaign_map_reprocess>
</field>
<field>
<field_uuid>{c338dc85-2201-4045-b11e-3c1a47d88554}</field_uuid>
<primary_key>0</primary_key>
<name>icon_override</name>
<field_type>text</field_type>
<required>0</required>
<max_length>255</max_length>
<requires_startpos_reprocess>0</requires_startpos_reprocess>
<requires_campaign_map_reprocess>0</requires_campaign_map_reprocess>
</field>
</root>
