<?xml version="1.0" encoding="UTF-8" standalone="no"?>
<!DOCTYPE TWaD_audio_campaign_environment_looping_sounds>
<root>
<edit_uuid>b230e85a-4a15-4aa7-88f7-e1f2eedabf3d</edit_uuid>
<agf_special_dependencies></agf_special_dependencies>
<field>
<field_uuid>{c42a0784-2726-4524-a325-973b2d152924}</field_uuid>
<primary_key>1</primary_key>
<name>key</name>
<field_type>text</field_type>
<required>1</required>
<max_length>255</max_length>
<agf_link_to_dependency>0</agf_link_to_dependency>
<agf_link_to_dependents>0</agf_link_to_dependents>
<agf_done>0</agf_done>
<requires_startpos_reprocess>0</requires_startpos_reprocess>
<requires_campaign_map_reprocess>0</requires_campaign_map_reprocess>
</field>
<field>
<field_uuid>{5cec1922-c649-433f-b56d-fb4db9d1199d}</field_uuid>
<primary_key>0</primary_key>
<name>start_event</name>
<field_type>text</field_type>
<fragment_path>sound/events</fragment_path>
<required>1</required>
<max_length>255</max_length>
<agf_link_to_dependency>0</agf_link_to_dependency>
<agf_link_to_dependents>0</agf_link_to_dependents>
<agf_done>0</agf_done>
<requires_startpos_reprocess>0</requires_startpos_reprocess>
<requires_campaign_map_reprocess>0</requires_campaign_map_reprocess>
</field>
<field>
<field_uuid>{a0ce91a3-a853-4875-9ee4-23816b875dda}</field_uuid>
<primary_key>0</primary_key>
<name>stop_event</name>
<field_type>text</field_type>
<fragment_path>sound/events</fragment_path>
<required>1</required>
<max_length>255</max_length>
<agf_link_to_dependency>0</agf_link_to_dependency>
<agf_link_to_dependents>0</agf_link_to_dependents>
<agf_done>0</agf_done>
<requires_startpos_reprocess>0</requires_startpos_reprocess>
<requires_campaign_map_reprocess>0</requires_campaign_map_reprocess>
</field>
<field>
<field_uuid>{91545939-50cd-443f-9732-3e2ab9a7c104}</field_uuid>
<primary_key>0</primary_key>
<name>intensity_rtpc</name>
<field_type>text</field_type>
<required>0</required>
<max_length>255</max_length>
<agf_link_to_dependency>0</agf_link_to_dependency>
<agf_link_to_dependents>0</agf_link_to_dependents>
<agf_done>0</agf_done>
<requires_startpos_reprocess>0</requires_startpos_reprocess>
<requires_campaign_map_reprocess>0</requires_campaign_map_reprocess>
</field>
</root>
