<?xml version="1.0" encoding="UTF-8" standalone="no"?>
<!DOCTYPE TWaD_ceo_triggers>
<root>
<edit_uuid>c39a53f4-9ae8-4775-a808-130ea197202c</edit_uuid>
<include_all_records_in_retail>1</include_all_records_in_retail>
<field>
<field_uuid>{d9bc422f-dc8a-44c9-95fa-e0941092710e}</field_uuid>
<primary_key>1</primary_key>
<name>key</name>
<field_type>text</field_type>
<required>1</required>
<max_length>255</max_length>
<requires_startpos_reprocess>0</requires_startpos_reprocess>
<requires_campaign_map_reprocess>0</requires_campaign_map_reprocess>
</field>
<field>
<field_uuid>{fff420e3-0285-4f3b-8d9c-1da5b3da5f37}</field_uuid>
<primary_key>0</primary_key>
<name>target_location</name>
<field_type>text</field_type>
<required>1</required>
<max_length>255</max_length>
<column_source_column>key</column_source_column>
<column_source_table>ceo_template_manager_types</column_source_table>
<requires_startpos_reprocess>0</requires_startpos_reprocess>
<requires_campaign_map_reprocess>0</requires_campaign_map_reprocess>
</field>
<field>
<field_uuid>{76d6e3ad-2d5a-4ae2-807f-b9c78d6dad08}</field_uuid>
<primary_key>0</primary_key>
<name>payload_description</name>
<field_type>text</field_type>
<required>0</required>
<default_value>placeholder</default_value>
<max_length>536870910</max_length>
<requires_startpos_reprocess>0</requires_startpos_reprocess>
<requires_campaign_map_reprocess>0</requires_campaign_map_reprocess>
</field>
</root>
