<?xml version="1.0" encoding="UTF-8" standalone="no"?>
<!DOCTYPE TWaD_campaign_map_attritions>
<root>
<edit_uuid>3fb8c108-2b2a-4632-a302-1332cbbe7eb7</edit_uuid>
<include_all_records_in_retail>1</include_all_records_in_retail>
<field>
<field_uuid>{50b8cd74-fa04-494c-a6a2-6c80eebdf807}</field_uuid>
<primary_key>1</primary_key>
<name>key</name>
<field_type>text</field_type>
<required>1</required>
<max_length>255</max_length>
<requires_startpos_reprocess>1</requires_startpos_reprocess>
<requires_campaign_map_reprocess>1</requires_campaign_map_reprocess>
</field>
<field>
<field_uuid>{c67b2c2d-62ce-437b-9f81-fcc168abe24f}</field_uuid>
<primary_key>0</primary_key>
<name>type</name>
<field_type>text</field_type>
<required>1</required>
<max_length>255</max_length>
<column_source_column>key</column_source_column>
<column_source_table>campaign_map_attrition_types</column_source_table>
<requires_startpos_reprocess>1</requires_startpos_reprocess>
<requires_campaign_map_reprocess>1</requires_campaign_map_reprocess>
</field>
<field>
<field_uuid>{095f5cd8-7a17-48b7-85e2-3dc549880376}</field_uuid>
<primary_key>0</primary_key>
<name>damage</name>
<field_type>text</field_type>
<required>1</required>
<max_length>255</max_length>
<column_source_column>key</column_source_column>
<column_source_table>campaign_map_attrition_damages</column_source_table>
<requires_startpos_reprocess>0</requires_startpos_reprocess>
<requires_campaign_map_reprocess>0</requires_campaign_map_reprocess>
</field>
<field>
<field_uuid>{51145e0d-5a41-430c-b59f-eb7c0d7443a5}</field_uuid>
<primary_key>0</primary_key>
<name>campaign_map_tooltip</name>
<field_type>text</field_type>
<required>0</required>
<max_length>20000</max_length>
<requires_startpos_reprocess>0</requires_startpos_reprocess>
<requires_campaign_map_reprocess>0</requires_campaign_map_reprocess>
</field>
<field>
<field_uuid>{f1794b12-22b6-4a80-acc3-7eb7872c2f6c}</field_uuid>
<primary_key>0</primary_key>
<name>unit_card_tooltip</name>
<field_type>text</field_type>
<required>0</required>
<max_length>20000</max_length>
<requires_startpos_reprocess>0</requires_startpos_reprocess>
<requires_campaign_map_reprocess>0</requires_campaign_map_reprocess>
</field>
<field>
<field_uuid>{d530df79-611d-40bf-b25b-87699b4150fa}</field_uuid>
<primary_key>0</primary_key>
<name>unit_immunity_text</name>
<field_type>text</field_type>
<required>0</required>
<max_length>20000</max_length>
<requires_startpos_reprocess>0</requires_startpos_reprocess>
<requires_campaign_map_reprocess>0</requires_campaign_map_reprocess>
</field>
<field>
<field_uuid>{da37a1b1-542f-4bb1-9595-e848d78db59e}</field_uuid>
<primary_key>0</primary_key>
<name>is_snow</name>
<field_type>yesno</field_type>
<required>1</required>
<default_value>false</default_value>
<requires_startpos_reprocess>0</requires_startpos_reprocess>
<requires_campaign_map_reprocess>0</requires_campaign_map_reprocess>
</field>
<field>
<field_uuid>{0700427a-0264-4126-82d4-4a978c1eb83b}</field_uuid>
<primary_key>0</primary_key>
<name>show_warning_on_map</name>
<field_type>yesno</field_type>
<required>1</required>
<default_value>false</default_value>
<requires_startpos_reprocess>0</requires_startpos_reprocess>
<requires_campaign_map_reprocess>0</requires_campaign_map_reprocess>
</field>
</root>
