<?xml version="1.0" encoding="UTF-8" standalone="no"?>
<!DOCTYPE TWaD_ui_unit_stat_to_unit_castes>
<root>
<edit_uuid>8af28d6e-18c7-4484-87d9-5cdf494e9d21</edit_uuid>
<agf_special_dependencies></agf_special_dependencies>
<field>
<field_uuid>{1a2cd124-ebcf-4516-8256-64d64053ebcb}</field_uuid>
<primary_key>1</primary_key>
<name>stat</name>
<field_type>text</field_type>
<required>1</required>
<max_length>255</max_length>
<column_source_column>key</column_source_column>
<column_source_table>ui_unit_stats</column_source_table>
<encyclopaedia_export>1</encyclopaedia_export>
<agf_link_to_dependency>1</agf_link_to_dependency>
<agf_link_to_dependents>0</agf_link_to_dependents>
<agf_done>1</agf_done>
<requires_startpos_reprocess>0</requires_startpos_reprocess>
<requires_campaign_map_reprocess>0</requires_campaign_map_reprocess>
</field>
<field>
<field_uuid>{554e3de0-b427-4bf1-bafa-6eaf983cdaa3}</field_uuid>
<primary_key>1</primary_key>
<name>unit_caste</name>
<field_type>text</field_type>
<required>1</required>
<max_length>255</max_length>
<column_source_column>caste</column_source_column>
<column_source_table>unit_castes</column_source_table>
<encyclopaedia_export>1</encyclopaedia_export>
<agf_link_to_dependency>0</agf_link_to_dependency>
<agf_link_to_dependents>1</agf_link_to_dependents>
<agf_done>1</agf_done>
<requires_startpos_reprocess>0</requires_startpos_reprocess>
<requires_campaign_map_reprocess>0</requires_campaign_map_reprocess>
</field>
<field>
<field_uuid>{cee73dbf-a583-4a6c-9b39-7e85c26d4448}</field_uuid>
<primary_key>0</primary_key>
<name>max_value_override</name>
<field_type>integer</field_type>
<required>1</required>
<encyclopaedia_export>1</encyclopaedia_export>
<agf_link_to_dependency>0</agf_link_to_dependency>
<agf_link_to_dependents>0</agf_link_to_dependents>
<agf_done>0</agf_done>
<requires_startpos_reprocess>0</requires_startpos_reprocess>
<requires_campaign_map_reprocess>0</requires_campaign_map_reprocess>
</field>
</root>
