<?xml version="1.0" encoding="UTF-8" standalone="no"?>
<!DOCTYPE TWaD_campaign_group_civil_war_defection_loyalty_thresholds>
<root>
<edit_uuid>a76f617e-748b-466b-b545-177bf0146f0d</edit_uuid>
<include_all_records_in_retail>1</include_all_records_in_retail>
<field>
<field_uuid>{bfc12208-1a0f-48a9-ba7d-bafa9c1845fd}</field_uuid>
<primary_key>1</primary_key>
<name>campaign_group</name>
<field_type>text</field_type>
<required>1</required>
<max_length>255</max_length>
<column_source_column>id</column_source_column>
<column_source_table>campaign_groups</column_source_table>
<requires_startpos_reprocess>0</requires_startpos_reprocess>
<requires_campaign_map_reprocess>0</requires_campaign_map_reprocess>
</field>
<field>
<field_uuid>{f3787367-7815-42fe-8dcf-126d88f4b8c2}</field_uuid>
<primary_key>0</primary_key>
<name>loyalty_threshold_value</name>
<field_type>integer</field_type>
<required>1</required>
<requires_startpos_reprocess>0</requires_startpos_reprocess>
<requires_campaign_map_reprocess>0</requires_campaign_map_reprocess>
</field>
<field>
<field_uuid>{a36536d2-180a-4824-a752-d05034d79430}</field_uuid>
<primary_key>0</primary_key>
<name>spy_loyalty_threshold_value</name>
<field_type>integer</field_type>
<required>1</required>
<default_value>0</default_value>
<requires_startpos_reprocess>0</requires_startpos_reprocess>
<requires_campaign_map_reprocess>0</requires_campaign_map_reprocess>
</field>
<field>
<field_uuid>{e2c04415-9d97-46db-bb2b-58d69591f1ba}</field_uuid>
<primary_key>0</primary_key>
<name>spy_public_order_threshold_value</name>
<field_type>integer</field_type>
<required>1</required>
<default_value>0</default_value>
<requires_startpos_reprocess>0</requires_startpos_reprocess>
<requires_campaign_map_reprocess>0</requires_campaign_map_reprocess>
</field>
<field>
<field_uuid>{61e401b9-fb1b-4e58-bbb8-cbeb2b4fb71a}</field_uuid>
<primary_key>0</primary_key>
<name>public_order_threshold_value</name>
<field_type>integer</field_type>
<required>1</required>
<default_value>0</default_value>
<requires_startpos_reprocess>0</requires_startpos_reprocess>
<requires_campaign_map_reprocess>0</requires_campaign_map_reprocess>
</field>
</root>
