<?xml version="1.0" encoding="UTF-8" standalone="no"?>
<!DOCTYPE TWaD_campaign_effect_scope_categories>
<root>
<edit_uuid>632c78e5-6af8-47af-8638-dd781d7997af</edit_uuid>
<agf_special_dependencies>+*</agf_special_dependencies>
<field>
<field_uuid>{2856157a-37e0-4ceb-8c22-2f408bdf873b}</field_uuid>
<primary_key>1</primary_key>
<name>key</name>
<field_type>text</field_type>
<required>1</required>
<max_length>255</max_length>
<agf_link_to_dependency>0</agf_link_to_dependency>
<agf_link_to_dependents>0</agf_link_to_dependents>
<agf_done>0</agf_done>
<requires_startpos_reprocess>0</requires_startpos_reprocess>
<requires_campaign_map_reprocess>0</requires_campaign_map_reprocess>
</field>
<field>
<field_uuid>{50ff33b2-07b1-46fe-87a9-8bb7455e3afd}</field_uuid>
<primary_key>0</primary_key>
<name>name_localised</name>
<field_type>text</field_type>
<required>1</required>
<max_length>255</max_length>
<agf_link_to_dependency>0</agf_link_to_dependency>
<agf_link_to_dependents>0</agf_link_to_dependents>
<agf_done>0</agf_done>
<requires_startpos_reprocess>0</requires_startpos_reprocess>
<requires_campaign_map_reprocess>0</requires_campaign_map_reprocess>
</field>
<field>
<field_uuid>{0a8f35e8-0633-47a7-bba3-4f8d7ca07442}</field_uuid>
<primary_key>0</primary_key>
<name>sort_order</name>
<field_type>integer</field_type>
<required>1</required>
<agf_link_to_dependency>0</agf_link_to_dependency>
<agf_link_to_dependents>0</agf_link_to_dependents>
<agf_done>0</agf_done>
<requires_startpos_reprocess>0</requires_startpos_reprocess>
<requires_campaign_map_reprocess>0</requires_campaign_map_reprocess>
</field>
<field>
<field_uuid>{af109c32-5e99-4268-a125-471161b930fd}</field_uuid>
<primary_key>0</primary_key>
<name>category_icon</name>
<field_type>text</field_type>
<is_filename>1</is_filename>
<filename_relative_path>ui/campaign ui/effect_bundles/%.png</filename_relative_path>
<required>0</required>
<max_length>255</max_length>
<field_description>effect bundle icon for the category display</field_description>
<agf_link_to_dependency>0</agf_link_to_dependency>
<agf_link_to_dependents>0</agf_link_to_dependents>
<agf_done>0</agf_done>
<requires_startpos_reprocess>0</requires_startpos_reprocess>
<requires_campaign_map_reprocess>0</requires_campaign_map_reprocess>
</field>
</root>
