<?xml version="1.0" encoding="UTF-8" standalone="no"?>
<!DOCTYPE TWaD_cai_construction_system_template_assignment_policy_faction_status_overrides>
<root>
<edit_uuid>26f33c64-331a-499c-8165-044a300883c1</edit_uuid>
<field>
<field_uuid>{ec56c74d-136b-4e29-a7bd-4b86f9ead40a}</field_uuid>
<primary_key>1</primary_key>
<name>template_assignment_policy</name>
<field_type>text</field_type>
<required>1</required>
<max_length>255</max_length>
<column_source_column>key</column_source_column>
<column_source_table>cai_construction_system_province_template_assignment_policies</column_source_table>
<agf_link_to_dependency>0</agf_link_to_dependency>
<agf_link_to_dependents>1</agf_link_to_dependents>
<agf_done>1</agf_done>
</field>
<field>
<field_uuid>{d3556b57-e8ce-412e-af4d-a89813aa0ba1}</field_uuid>
<primary_key>1</primary_key>
<name>faction_status</name>
<field_type>text</field_type>
<required>1</required>
<max_length>255</max_length>
<column_source_column>faction_status</column_source_column>
<column_source_table>cai_faction_statuses</column_source_table>
<agf_link_to_dependency>1</agf_link_to_dependency>
<agf_link_to_dependents>0</agf_link_to_dependents>
<agf_done>1</agf_done>
</field>
<field>
<field_uuid>{39c388d6-44b7-436e-8694-b0b69e0f3fd5}</field_uuid>
<primary_key>0</primary_key>
<name>template_assignment_scheme</name>
<field_type>text</field_type>
<required>1</required>
<max_length>255</max_length>
<column_source_column>scheme_key</column_source_column>
<column_source_table>cai_construction_system_template_assignment_schemes</column_source_table>
<agf_link_to_dependency>1</agf_link_to_dependency>
<agf_link_to_dependents>0</agf_link_to_dependents>
<agf_done>1</agf_done>
</field>
</root>
