<?xml version="1.0" encoding="UTF-8"?>
<dataroot xmlns:od="urn:schemas-microsoft-com:officedata" xmlns:xsi="http://www.w3.org/2001/XMLSchema-instance" xsi:noNamespaceSchemaLocation="unit_class.xsd" export_time="Tue Jul 24 09:01:18 2018" revision="31" export_branch="C:/Users/Nicolas.Graber/AppData/Roaming/TWDaemon/1062/dave" export_user="bob">
<edit_uuid>77a6ffa7-ad07-4260-ab91-3c99b795d1fc</edit_uuid>
<unit_class record_uuid="{23cf3f01-4fed-4f7e-b74e-c4b39a8ce81a}" record_timestamp="1373012022586" record_key="art_fix">
<key>art_fix</key>
<onscreen state="HIDDEN" last_approved_text="Fixed Artillery" last_edit_user="bob">Fixed Artillery</onscreen>
<sort_priority>11</sort_priority>
<tooltip state="HIDDEN" last_approved_text="Fixed position artillery units that pack quite a punch, they are nevertheless very weak if engaged in melee." last_edit_user="bob">Fixed position artillery units that pack quite a punch, they are nevertheless very weak if engaged in melee.</tooltip>
</unit_class>
<unit_class record_uuid="{9590f6ee-b197-4a7a-b34e-42904292a285}" record_timestamp="1373012022556" record_key="art_fld">
<key>art_fld</key>
<onscreen state="HIDDEN" last_approved_text="Field Artillery" last_edit_user="bob">Field Artillery</onscreen>
<sort_priority>10</sort_priority>
<tooltip state="HIDDEN" last_approved_text="With a long range and able to cause great damage, field artillery can be moved slowly around the battlefield, but are very weak if engaged in melee." last_edit_user="bob">With a long range and able to cause great damage, field artillery can be moved slowly around the battlefield, but are very weak if engaged in melee.</tooltip>
</unit_class>
<unit_class record_uuid="{666132f2-08a9-4a37-864f-aa743a73e079}" record_timestamp="1373012022606" record_key="art_siege">
<key>art_siege</key>
<onscreen state="HIDDEN" last_approved_text="Siege Artillery" last_edit_user="bob">Siege Artillery</onscreen>
<sort_priority>12</sort_priority>
<tooltip state="HIDDEN" last_approved_text="Huge siege engines perfect for knocking down walls and gatehouses." last_edit_user="bob">Huge siege engines perfect for knocking down walls and gatehouses.</tooltip>
</unit_class>
<unit_class record_uuid="{26584111-8f95-4f0e-a859-9605f3bf9d50}" record_timestamp="1373012022366" record_key="cav_mel">
<key>cav_mel</key>
<onscreen state="HIDDEN" last_approved_text="Melee Cavalry" last_edit_user="bob">Melee Cavalry</onscreen>
<sort_priority>4</sort_priority>
<tooltip state="HIDDEN" last_approved_text="Although they are versatile units protected by shields, melee cavalry are weak against more specialised units." last_edit_user="bob">Although they are versatile units protected by shields, melee cavalry are weak against more specialised units.</tooltip>
</unit_class>
<unit_class record_uuid="{f250cb04-e1fc-4e39-9f6f-5d09c35cb10f}" record_timestamp="1373012022456" record_key="cav_mis">
<key>cav_mis</key>
<onscreen state="HIDDEN" last_approved_text="Missile Cavalry" last_edit_user="bob">Missile Cavalry</onscreen>
<sort_priority>5</sort_priority>
<tooltip state="HIDDEN" last_approved_text="Fast moving and with a long range, missile cavalry are great at harassing their enemies, but weak if pinned down in melee." last_edit_user="bob">Fast moving and with a long range, missile cavalry are great at harassing their enemies, but weak if pinned down in melee.</tooltip>
</unit_class>
<unit_class record_uuid="{b9fd107c-c28e-4c7d-95ad-a9515e121a4b}" record_timestamp="1373012022406" record_key="cav_shk">
<key>cav_shk</key>
<onscreen state="HIDDEN" last_approved_text="Shock Cavalry" last_edit_user="bob">Shock Cavalry</onscreen>
<sort_priority>3</sort_priority>
<tooltip state="HIDDEN" last_approved_text="The hammer to the infantry of any army, they are devastating when charged into the flank or rear of enemies." last_edit_user="bob">The hammer to the infantry of any army, they are devastating when charged into the flank or rear of enemies.</tooltip>
</unit_class>
<unit_class record_uuid="{96a385b1-aaba-4f4b-8441-c7af3c950019}" record_timestamp="1373012022386" record_key="chariot">
<key>chariot</key>
<onscreen state="HIDDEN" last_approved_text="Chariot" last_edit_user="bob">Chariot</onscreen>
<sort_priority>2</sort_priority>
<tooltip state="HIDDEN" last_approved_text="Fast moving units with a wide turning circle, they can punch through weak enemy units. They are vulnerable if pinned down in combat." last_edit_user="bob">Fast moving units with a wide turning circle, they can punch through weak enemy units. They are vulnerable if pinned down in combat.</tooltip>
</unit_class>
<unit_class record_uuid="{c72296bd-f85d-48ee-be6a-6edefddaf4eb}" record_timestamp="1369759606036" record_key="com">
<key>com</key>
<onscreen state="HIDDEN" last_approved_text="Command" last_edit_user="bob">Command</onscreen>
<sort_priority>0</sort_priority>
<tooltip state="HIDDEN" last_approved_text="These are small units that protect the general whilst he gets on with his job." last_edit_user="bob">These are small units that protect the general whilst he gets on with his job.</tooltip>
</unit_class>
<unit_class record_uuid="{652ec11d-2133-4f29-a576-28c6949afdb9}" record_timestamp="1373012022326" record_key="elph">
<key>elph</key>
<onscreen state="HIDDEN" last_approved_text="Elephant" last_edit_user="bob">Elephant</onscreen>
<sort_priority>1</sort_priority>
<tooltip state="HIDDEN" last_approved_text="There's nothing quite like an elephant to make a hole in an enemy line. Flaming projectiles and javelins are the best way to counter them." last_edit_user="bob">There's nothing quite like an elephant to make a hole in an enemy line. Flaming projectiles and javelins are the best way to counter them.</tooltip>
</unit_class>
<unit_class record_uuid="{d42ab4dd-df81-4666-86d9-3d5d1cbbcbf8}" record_timestamp="1373012022496" record_key="inf_mel">
<key>inf_mel</key>
<onscreen state="HIDDEN" last_approved_text="Melee Infantry" last_edit_user="bob">Melee Infantry</onscreen>
<sort_priority>7</sort_priority>
<tooltip state="HIDDEN" last_approved_text="Frontline soldiers trained for hand-to-hand combat with their enemies." last_edit_user="bob">Frontline soldiers trained for hand-to-hand combat with their enemies.</tooltip>
</unit_class>
<unit_class record_uuid="{d7ee3884-fc80-410f-a4eb-08fb69ec4287}" record_timestamp="1465998492938" record_key="inf_mis">
<key>inf_mis</key>
<onscreen state="HIDDEN" last_approved_text="Missile Infantry" last_edit_user="bob">Missile Infantry</onscreen>
<sort_priority>9</sort_priority>
<tooltip state="HIDDEN" last_approved_text="Long range units who provide support for melee units, but are themselves generally weak in close combat." last_edit_user="bob">Long range units who provide support for melee units, but are themselves generally weak in close combat.</tooltip>
</unit_class>
<unit_class record_uuid="{f7cbf5e6-e2c4-4213-bd43-84cc93c00e28}" record_timestamp="1373012022476" record_key="inf_pik">
<key>inf_pik</key>
<onscreen state="HIDDEN" last_approved_text="Pike Infantry" last_edit_user="bob">Pike Infantry</onscreen>
<sort_priority>6</sort_priority>
<tooltip state="HIDDEN" last_approved_text="Long pikes make these troops deadly from the front but vulnerable if flanked. They are highly effective against cavalry." last_edit_user="bob">Long pikes make these troops deadly from the front but vulnerable if flanked. They are highly effective against cavalry.</tooltip>
</unit_class>
<unit_class record_uuid="{499c142b-ac76-475d-ad50-81876fde1167}" record_timestamp="1373012022516" record_key="inf_spr">
<key>inf_spr</key>
<onscreen state="HIDDEN" last_approved_text="Spear Infantry" last_edit_user="bob">Spear Infantry</onscreen>
<sort_priority>8</sort_priority>
<tooltip state="HIDDEN" last_approved_text="Solid defensive infantry protected by shields, they are very good when ranged against cavalry." last_edit_user="bob">Solid defensive infantry protected by shields, they are very good when ranged against cavalry.</tooltip>
</unit_class>
<unit_class record_uuid="{9472d39f-e811-4ee3-b8c8-540543cfdbc0}" record_timestamp="1373012022626" record_key="shp_art">
<key>shp_art</key>
<onscreen state="HIDDEN" last_approved_text="Artillery Ship" last_edit_user="bob">Artillery Ship</onscreen>
<sort_priority>1</sort_priority>
<tooltip state="HIDDEN" last_approved_text="These ships can do a lot of damage from long range, but can be neutralised by boarding and ramming." last_edit_user="bob">These ships can do a lot of damage from long range, but can be neutralised by boarding and ramming.</tooltip>
</unit_class>
<unit_class record_uuid="{1e71d42b-477f-4250-b672-c8a643293100}" record_timestamp="1373012022646" record_key="shp_mel">
<key>shp_mel</key>
<onscreen state="HIDDEN" last_approved_text="Melee Ship" last_edit_user="bob">Melee Ship</onscreen>
<sort_priority>2</sort_priority>
<tooltip state="HIDDEN" last_approved_text="Perfect for taking out enemy ships, but have to close quickly and board to be successful. " last_edit_user="bob">Perfect for taking out enemy ships, but have to close quickly and board to be successful. </tooltip>
</unit_class>
<unit_class record_uuid="{12fa9fd5-832a-44a7-8d51-f70ad395ab19}" record_timestamp="1373012022666" record_key="shp_mis">
<key>shp_mis</key>
<onscreen state="HIDDEN" last_approved_text="Missile Ship" last_edit_user="bob">Missile Ship</onscreen>
<sort_priority>3</sort_priority>
<tooltip state="HIDDEN" last_approved_text="Enemy ships can be showered with their projectiles, but they must steer clear of enemy melee ships." last_edit_user="bob">Enemy ships can be showered with their projectiles, but they must steer clear of enemy melee ships.</tooltip>
</unit_class>
<unit_class record_uuid="{83740ea7-cada-4754-8bc0-e33a6ffec123}" record_timestamp="1373012022686" record_key="shp_trn">
<key>shp_trn</key>
<onscreen state="HIDDEN" last_approved_text="Transport Ship" last_edit_user="bob">Transport Ship</onscreen>
<sort_priority>4</sort_priority>
<tooltip state="HIDDEN" last_approved_text="Slow but with plenty of space, they do their job well. Just remember that they aren't warships." last_edit_user="bob">Slow but with plenty of space, they do their job well. Just remember that they aren't warships.</tooltip>
</unit_class>
<unit_class record_uuid="{8cfe8f7f-db53-4c26-a523-949ac02de8da}" record_timestamp="1373012022706" record_key="spcl">
<key>spcl</key>
<onscreen state="HIDDEN" last_approved_text="Special" last_edit_user="bob">Special</onscreen>
<sort_priority>13</sort_priority>
<tooltip state="HIDDEN" last_approved_text="Nothing says &quot;surprise!&quot; like unleashing animals on the battlefield." last_edit_user="bob">Nothing says &quot;surprise!&quot; like unleashing animals on the battlefield.</tooltip>
</unit_class>
</dataroot>
